extract_icon/__init__.py
extract_icon-0.0.4.dist-info/DESCRIPTION.rst
extract_icon-0.0.4.dist-info/METADATA
extract_icon-0.0.4.dist-info/RECORD
extract_icon-0.0.4.dist-info/WHEEL
extract_icon-0.0.4.dist-info/metadata.json
extract_icon-0.0.4.dist-info/top_level.txt
