Metadata-Version: 1.1
Name: extract-icon
Version: 0.0.4
Summary: Extract Icon from PE Executable File
Home-page: https://www.python.org/
Author: Fadhil Mandaga
Author-email: firodj@gmail.com
License: UNKNOWN
Keywords: extract icon executable
Platform: UNKNOWN
Classifier: Development Status :: 3 - Alpha
Classifier: Environment :: Console
Classifier: Operating System :: OS Independent
Classifier: Topic :: Utilities
